classification_transformers/customtransformers.py
classification_transformers-0.0.1.dist-info/METADATA
classification_transformers-0.0.1.dist-info/WHEEL
classification_transformers-0.0.1.dist-info/top_level.txt
classification_transformers-0.0.1.dist-info/RECORD
