Metadata-Version: 2.1
Name: classification-transformers
Version: 0.0.1
Summary: Use the package for easy configuration of the huggingface models
Home-page: https://github.com/harshad317/custom_transformers
Author: Harshad Patil
Author-email: hhpatil001@gmail.com
Keywords: pypi,mikes_toolbox,tutorial
Classifier: License :: OSI Approved :: MIT License
Classifier: Programming Language :: Python :: 3.7
Classifier: Programming Language :: Python :: 3.9
Classifier: Programming Language :: Python :: 3.10
Requires-Dist: requests
